{"linhas":[{"numero":"01","nome":"Linha 01","ida":["05:15  Epitácio Pessoa (Pão de Açucar)","05:20  Ferry Boat - Av. Rei Alberto I - Rua Governador Fernando Costa","05:25  Praça Eng. José Rebouças - Av. Aristóteles Menezes - Rua Caramuru","05:30  Av. Pedro Lessa até Canal 4 - Canal 4 até Praça Palmares","05:40  Av. Afonso Pena","05:45  Av. Francisco Glicério até Canal 1 - Canal 1 - Santa Casa - Túnel","05:55  Praça dos Andradas","06:00  Anchieta / Imigrantes","06:50  Metrô Imigrantes   (Av. do Estado - Norma Gianotti - Marques de Sv.)","07:40  Bolsão Barra Funda","08:00  Av. Santa Marina"],"volta":["19:20  Metrô Conceição","20:15  Av. Martins Fontes (Posto Marilú)","20:20  Túnel - Santa Casa - Canal 1","20:25  Av. Francisco Glicério","20:35  Av. Afonso Pena - Av. Pedro Lessa - Av. Epitácio Pessoa","20:50  Ferry Boat","21:10  Av. da Praia até Av. Pres. Wilson - Av. Antonio Emmerich"]},{"numero":"02","nome":"Linha 02","ida":["04:40   F. Glicério c/ Canal 2","04:43   Floriano Peixoto c/ Ana Costa","04:45   Floriano Peixoto c/ Canal 3","04:50   Eptácio c/ Oswaldo Cochrane","04:55   Ferry Boat","04:58   Rei Alberto - Canal 7 - Canal 6 até Pedro Lessa (Pizzaria)","05:07   Pedro Lessa até Canal 4 - Pça Palmares","05:10   F. Glicério c/ Ana Costa","05:12   F. Glicério c/ Canal 2","05:15   F. Glicério c/ Canal 1","05:20   Pça dos Andrades","05:25   Anchieta / Imigrantes","06:15   M. Conceição","06:30   M. Imigrantes","06:40   Av. do Estado – CTO","07:05   Estação Barra Funda"],"volta":["16:45   M. Imigrantes","17:15   M. Conceição","18:20   Posto Marilú","18:30   Santa Casa","18:40   Canal 2 c/ Espírito Santo","18:42   Espirito Santo c/ Ana Costa","18:45   Cunha Moreira c/ Sen. Feijó","18:50   F. Glicério c/ Canal 3","18:55   P. Lessa c/ Canal 4","19:00   P. Lessa c/ Oswaldo Cochrane","19:05   P. Lessa c/ Canal 5","19:10   Canal 6"]},{"numero":"03","nome":"Linha 03","ida":["06:10  Ferry Boat","06:15  Av. Rei Alberto I até Canal 6 - Canal 6 até Pedro Lessa","06:25  Av. Pedro Lessa até Canal 4 - Canal 4 até Praça Palmares","06:30  Av. Afonso Pena","06:35  Av. Francisco Glicério até Canal 1 - Canal 1 - Santa Casa – Túnel","06:45  Praça dos Andradas","06:50  Anchieta / Imigrantes","07:45  Metrô Conceição","08:05  Metrô Imigrantes s"],"volta":["18:00  Metrô Conceição","19:00  Av. Martins Fontes (Posto Marilú)","19:05  Av. São Francisco","19:10  Av. Senador Feijó","19:15  Av. Francisco Glicério","19:20  Av. Conselheiro Nébias","19:40  Av. Epitácio Pessoa  até  Ferry Boat","19:50  Av. Pedro Lessa até Canal 4"]},{"numero":"04","nome":"Linha 04","ida":["07:00  Ferry Boat","07:05  Av. Rei Alberto I até Canal 6","07:15  Av. da Praia até Av. Conselheiro Nébias","07:20  Av. Conselheiro Nébias até Av. Francisco Glicério","07:25  Av. Francisco Glicério até Canal 1","07:35  Canal 1 - Santa Casa - Túnel - Praça dos Andradas","07:40  Anchieta / Imigrantes","08:30  Metrô Conceição","08:45  Metrô Imigrantes"],"volta":["17:45  Metrô Conceição","18:45  Av. Martins Fontes (Posto Marilú)","18:50  Av. São Francisco","18:55  Av. Senador Feijó","19:00  Av. Francisco Glicério","19:10  Av. Conselheiro Nébias","19:20  Av. Dr. Epitácio Pessoa / Ferry Boat","19:35  Av. Pedro Lessa até Canal 4"]},{"numero":"05","nome":"Linha 05","ida":["05:50   Ferry Boat - Av. Rei Alberto I até Dino Bueno","06:00   Av. Pedro Lessa até Canal 4 - Canal 4 até Rua Bento de Abreu","06:05   Rua Bento de Abreu até Azevedo Sodré","06:10   Av. Ana Costa até Pedro Américo","06:12   Rua Pedro Américo até Canal 2)","06:15   Canal 2 até Av. Francisco Glicério","06:17   Canal 1","06:25   Santa Casa - Túnel - Praça dos Andradas","06:35   Casqueiro /Anchieta","07:25   Metrô Conceição","07:30   Bandeirantes (Aeroporto)","07:45   Bandeirantes c/  Ver. José Diniz","08:15   Berrini / Ponte do Morumbi","08:20   Cenesp (Extra)","08:25   Marginal Pinheiros – Alexandre Dumas"],"volta":["17:10   Carrefour (Estação Granja Julieta)","17:15   Ponte do Morumbii","17:20   Av. Luiz Carlos Berrini","17:25   Bandeirantes (Bolsão)  )","17:35   Bandeirantes c/  Ver. José Diniz","17:50   Conceição","19:05   Av. Martins Fonte (Posto Marilú)","19:15   Túnel - Santa Casa - Canal 1","19:25   Av. Francisco Glicério - Alexandre Herculano","19:30   Av. Washington Luiz - Pedro de Toledo","19:35   Av. Epitácio Pessoa até canal 4","19:40   Canal 4 até Av. Pedro Lessa","19:50   Pedro Lessa até Ferry Boat"]},{"numero":"06","nome":"Linha 06","ida":["07:30  Ferry Boat","07:35  Av. Rei Alberto I até Canal 6 - Canal 6 até Pedro Lessa","07:45  Av. Pedro Lessa até Canal 4 - Canal 4 até Praça Palmares","07:50  Av. Afonso Pena c/ Canal 3","07:55  Av. Francisco Glicério até Canal 1 - Canal 1 - Santa Casa – Túnel","08:05  Praça dos Andradas","08:10  Anchieta / Imigrantes","09:00  Metrô Conceição"],"volta":["19:40  Metrô Conceição","20:30  Av. Martins Fontes (Posto Marilu)","20:40  Túnel - Santa Casa - Canal 1","20:45  Av. Francisco Glicério","20:55  Av. Afonso Pena - Av. Pedro Lessa - Av. Epitácio Pessoa","21:05  Ferry Boat","21:20  Av. da Praia até Av. Pres. Wilson - Av. Antonio Emmerich"]},{"numero":"07","nome":"Linha 07","ida":["05:45   Ferry Boat","05:47   Rei Alberto - Canal 7 – Dino Bueno – Pad. Luar de Prata","05:48   Praça Rebouças / Padaria - Av. Pedro Lessa","05:50   Av. Pedro Lessa – Canal 6","05:52   Av. Pedro Lessa – Canal 5","05:54   Av. Pedro Lessa – Senador Dantas","05:55   Av. Pedro Lessa – Canal 4 - Praça Palmares - Av. Afonso Pena","05:58   Av. Afonso Pena - Av. Conselheiro Nébias","05:59   Canal 3 - Av. Francisco Glicério","06:01   Av. Francisco Glicério – Ana Costa / EXTRA","06:03   Av. Francisco Glicério – Canal 2","06:05   Av. Francisco Glicério - Canal 1","06:10   Canal 1 – Carvalho de Mendonça – Curvão","06:13   Canal 1 – Santa Casa","06:17   Santa Casa – Túnel – Praça do Andradas","06:21   Posto Marilu","06:26   Jardim Casqueiro – Passarela","06:34   Imigrantes / Balança","07:10   Túnel Complexo Maria Maluf – Tancredo Neves","07:15   Rua Euclides Pinheiro / Rua Abauna / Pça. Ademar Dutra","07:25   Juntas Provisórias / Inhaia Melo / Salim Farah Maluf","07:35   Rua Demétrio Ribeiro / Rua Coelho Lisboa / Pça. Silva Romero)","07:37   Rua Serra de Bragança / Rua Itapura / Rua Tijuco Preto / Av. Azevedo","07:38   Av.Azevedo – Celso Garcia","07:40   Av.Celso Garcia / Rua Baguari / Rua Ururai","07:42   Rua Ururai - ITAUTEC","07:45   Rua Sabatino Nastari / Rua Tuiuti","07:50   Metrô Tatuapé (Rua Catiguá)","07:55   R. Padre Adelino / Largo Ubirajara / R. Belarmino Matos","08:05   Lg. São José do Belém (Estação Belenzinho)","08:07   R. Cajuru / R. Visc. de Parnaíba / R.Martim Afonso","08:10   Av.Celso Garcia / Lgo. da Concórdia",""],"volta":["17:25   Largo Senador M. Barros / Celso Garcia / Rua Belémm","17:27   Rua Siqueira Bueno - Vd. Guadalajara","17:30   Radial Leste / Rua Tuiutii","17:45   Pça. Silvio Romero","17:47   Rua Isidoro Tinoco / Rua Pe.Estevão Pernet / Av. Azevedoo","17:48   Av. Azevedo – Celso Garcia","17:50   Celso Garcia / Rua Baguari / Rua Ururai   i","18:05   Rua Ururai – ITAUTEC","18:07   Rua Sabatino Nastari / Rua Tuiuti / Celso Garcia a","18:10   Metrô Tatuapé (Rua Catiguá)","18:55   Av. Salim Farah Maluf / Anhaia Melo / Juntas Provisórias – Anchieta  a","19:45   Av. Martins Fontes (Posto Marilú)","19:50   Túnel - Santa Casa - Canal 11","20:05   Canal 1 - Av. Francisco Glicério – Canal 4 / Praça Palmares","20:15   Canal 4 - Av. Pedro Lessa - Canal 7 7","20:25   Ferry Boat"]},{"numero":"08","nome":"Linha 08","ida":["05:00  Av. Antonio Emmerich - Av. pres. Wilson","05:10  Av. da Praia - Canal 4 - Av. Pedro Lessa","05:15  Av. Pedro Lessa até Canal 6","05:23  Praça Rebouças - Dino Bueno - Av. Bancários - Canal 6","05:26  Guaião - Cons. Ribas - Cons. Lafayaete","05:30  Canal 4 - Praça Palmares - Afonso Penas","05:32  Afonso Pena - Francisco Glicério - Canal 3","05:35  Canal 3 - Azevedo Sodré - Ana Costa","05:38  Euclides da Cunha - Canal 1 +","05:45  Canal 1 - Santa Casa - Praça dos Andradas","05:50  Posto Marilú","06:05  Cubatão - Jardim Casqueiro 07:15  RODOANELL","07:30  Rodovia Castelo Branco","07:40  Alphaville - Al. Rio Negro","07:45  Alphaville - Al. Araguaia (CPM)","07:50  Alphaville - Bradesco","08:00  Alphaville - Green Vale (Centro Empresarial)"],"volta":["16:55  Alphaville - Green Vale (Centro Empresarial)  )","17:00  Alphaville -Bradesco","17:15  Alphaville - Al. Rio Negro - Av. Tamboré","17:20  Saída de Alphaville - Castelo Branco","17:25  RODOANEL","19:10  Posto Marilú - Praça dos Andradas","19:27  Túnel - Santa Casa - Canal 1 - Francisco Glicério","19:40  Av. Afonso Pena - Canal 4","19:45  Av. Pedro Lessa até Canal 6","19:55  Praça Rebouças - Dino Bueno – Bancários","20:00  Canal 6 - Guaião - Cons/ Ribas - Cons. Lafayete","20:05  Canal 4 - Av. da Praia","20:15  Canal 4 - 3 - 2 - 1 - Divisa","20:30  São Vicente - Av. Pres. Wilson","20:35  São Vicente - Carrefour"]},{"numero":"09","nome":"Linha 09","ida":["05:25   Av. Afonso Pena - Senador Dantas","05:28   Av. Pedro Lessa até Canal 6","05:30   Av. dos Portuários - Ferry Boat","05:35   Canal 6 - Av. da Praia","05:40   Rua Alexandre Martins - Cons. Lafayete - Canal 4","05:45   Rua Bento de Abreu - Azevedo Sodré","05:55   Canal 3 - Alexandre Herculano - Francisco Glicério","06:02   Canal 1 - Santa Casa - Túnel","06:05   Praça dos Andradas","06:10   Saboó - Posto Marilú","06:50   Metrô Imigrantes","07:05   Av. Dom Pedro I","07:10   Av. do Estado","07:15   Metro D. Pedro II","07:30   Metrô Armênia","07:35   Av. Olavo Fontoura"],"volta":["17:02   Praça Dirceu de Lima","17:05   Brás Leme - Olavo Fontoura","17:15   Av. do Estado","17:40   Metrô Imigrantes","18:45   Av. Martins Fontes (Posto Marilú)","19:00   Túnel - Santa Casa - Canal 1","19:10   Av. Francisco Glicério","19:20   Gov. Pedro de Toledo - Canal 4 - Av. Pedro Lessa","19:30   Av. Pedro Lessa - Canal 6 - Ferry Boat","19:40   Bancários - Canal 6"]},{"numero":"11","nome":"Linha 11","ida":["05:05  Antonio Emmerich – Quartell","05:10  Presidente Wilson – Pão de Açúcar","05:15   Divisa a","05:20   Praia Canal 1 - Floriano Peixoto - Galeão Carvalhal","05:25   Epitácio Pessoa – Bancários s","05:30   Rei Alberto - Fernando Costa – Pça. Rebouças","05:35   Pedro Lessa - Senador Dantas – Liberdade – Praça Palmaress","05:38   Afonso Pena com Conselheiro Nébias (UNIMES) – Canal 3 (Paola)","05:40   Ana Costa - Francisco Glicério  o","05:45   Canal 1 (Drogaria Iporanga) – Posto com Canal 2 (Portuguesa)","05:50   Santa Casa - Praça dos Andradas s","06:00   Marilú - Ponte do Casqueiro","06:50   Metro Conceiçãoo","07:00   Engº Armando Arruda Pereira – Pedro Bueno","07:10   João P. Cardoso - Tamoios (GOL/VASP) – Washington Luizz","07:20   Rubem Berta - Aeroporto de Congonhas – Jesuíno Maciel","07:30   Porto Alegre - Bandeirantes – Berrini  i","07:40   Av. Chucri Zaidan – Ponte do Morumbi","07:50   Marginal Pinheiros  s","08:00   Cenesp"],"volta":["17:30   Cenesp - Box 5","17:35   Marginal Pinheiros - Estação de Trem Granja Julieta","17:38   Ponte do Morumbi","17:40   Marginal Pinheiros – Águas Espraiadas","17:50   Berrinii","18:00   Bandeirantes","18:15   Metrô Conceição  o","19:15   Posto Marilú – Saboó","19:20   Senador Feijó – 7 de Setembro   o","19:30   Silva Jardim - Av. Afonso Pena - Canal 4/Pedro Lessa (Sta.Cecília)","19:35   Av. Pedro Lessa - Canal 4 -5 - 6 – Rebouças – Fernando Costaa","19:40   Rei Alberto - Bancários –Epitácio Pessoa - Canal 6","19:45   Praia FATEC - Praia Canal 5 – Canal 4 (Igreja Embaré) s","19:55   Praia Canal 3 - Gonzaga – Canal 2","20:00   Praia Canal 1 – Divisa – Presidente Wilson – Frei Gaspar   r"]},{"numero":"12","nome":"Linha 12","ida":["05:40  Av. Pedro Lessa com Senador Dantas","05:45  Gov. Fernando Costa c/ Rei Alberto I","06:00  Av. dos Bancários - Pizza Cristal","06:05  Praia Canal 5 - Cons. Lafaiete","06:10  Av. Afonso Pena - Praça Palmares - Conselheiro Nébias","06:15  Canal 3 - Av. Francisco Glicério","06:20  Canal 1 - João Caetano- Praça Curvão","06:25  Santa Casa - Praça dos Andradas - Marilú","07:25  Metrô Imigrantes"],"volta":["18:10  Metrô Conceição","19:00  Posto Marilú","19:10  Santa Casa","19:15  Canal 1 - Av. Francisco Glicério","19:20  Canal 2 - Av. Francisco Flicério","19:25  Canal 3 - Av. Francisco Glicério","19:30  Av. Pedro Lessa - Canal 4","19:35  Av. Pedro lessa - Canal 6 - Rebouças","19:45  Ponta da Praia - Ferry Boat"]},{"numero":"13","nome":"Linha 13","ida":["05:15   Av. Epitácio Pessoa - Canais 4 / 5 / 6","05:20   Av. Bancários - Rua Rei Alberto I - Pç. Rebouças","05:25   Av. Pedro Lessa c/ Canal 6","05:30   Av. Pedro Lessa c/ Canal 4","05:35   Av. Afonso Pena c/ Av. Cons. Nébias","05:40   Av. Fancisco Glicério c/ canal 3  -  Av. Ana Costa  - Canal 2  - Canal 1","05:50   Santa Casa - Praça dos Andradas","05:55   Posto Marilú","06:00   Jardim Casqueiro - Vila dos Pescadores","06:50   Metrô Imigrantes","06:55   Av. Teresa Cristina","07:00   Av. do Estado","07:15   Av. Santos Dumond","07:20   Av Olavo Fontoura - Campo de Marte","07:25   Ponte da Casa Verde","07:30   Metrô Barra Funda (Memorial da América Latina)","07:35   Av. Francisco Matarazzo - Shopping West Plaza","07:40   Rua Guaicurus","07:45   Mercado da Lapa","07:50   Rua John Harrisom - Estação da Lapa","07:55   Av. Monte Pascoal – Anhanguera","08:00   Vila Anastácio - Sádia"],"volta":["17:10   Vila Anastácio Sadia","17:15   Marginal Tiete - Alstom - Siemens","17:20   Av. Ermano Marchetti - Mc Donald's","17:30   Viaduto Antartica - Shopping West Plaza","17:40   Metrô Barra Funda - Memorial da América Latina","17:45   Ponte do Pacaembú","17:50   Rua Norma P. Ganottii - Rua Sergio Tomás","18:00   Av. do Estado","18:20   Juntas Provisórias","18:25   Anchieta","19:10   Jardim Casqueiro - Vila dos Pescadores","19:20   Posto Marilu","19:25   Túnel - Santa Casa - Canal 1","19:35   Av. Francisco Glicério - Canal 2","19:40   Av. Francisco Glicério com Ana Costa","19:45   Av. Afonso Pena com Av. Cons. Nébias","19:50   Canal 4 - Av. Pedro Lessa com canal 5 e 6","19:55   Praça Rebouças","20:00   Ferry Boat","20:10   Praia em frente ao Colégio Escolástica Rosa"]},{"numero":"14","nome":"Linha 14","ida":["05:40  R. Galeão Carvalhal / Banespa","05:43  Av. Epitácio Pessoa / Oswaldo Cochrane","05:45  Av. Epitácio Pessoa / Sampaio Moreira / Alexandre Martins","05:48  Av. dos Bancários / R. Trabussi","05:49  Rei Alberto / Av. Fernando Costa","05:50  Av. Fernando Costa / Praça Rebouças","05:52  Av. Pedro Lessa / Canal 6 – Barateiro","05:56  Av. Pedro Lessa / Panificadora Portela","05:58  Av. Pedro Lessa / Alexandre Martins / Canal 5","06:00  Av. Pedro Lessa / Benjamin Constant / Praça Fernando Prestes","06:02  Afonso Pena / Senador Dantas","06:07  Afonso Pena / Conselheiro Nébias","06:08  Av. Francisco Glicério / Canal 3","06:11  Av. Francisco Glicério / Ana Costa","06:13  Canal 1 /Francisco Glicério","06:14  Canal 1 / João Caetano","06:15  Canal 1 / Duque de Caxias","06:16  Canal 1 / Carvalho de Mendonça","06:20  Santa Casa / Mc Donald’s / Túnel","06:25  Av. Martins Fontes / Marilú","07:20  Metrô Imigrantes"],"volta":["17:50  Metrô Imigrantes","18:45  Casqueiro","18:50  Marilú","18:54  Túnel","18:55  Lateral Mc Donald´s","18:58  R. Lucas Fortunato / Rua Júlio Conceição","19:02  R. Lucas Fortunato /Av. Senador Feijó","19:04  R. Dona Luisa Macuco","19:08  Rua Silva Jardim / Rua Borges","19:09  Rua Silva Jardim / Av. Conselheiro Rodrigues Alves","19:11  Afonso Pena / Palmares / Senador Dantas","19:14  Senador Dantas / Pedro Lessa","19:16  Av. Pedro Lessa / Oswaldo Cochrane","19:17  Av. Pedro Lessa / Canal 5","19:19  Av. Pedro Lessa / Pizzaria (antiga Vila Jóquei)","19:20  Av. Pedro Lessa / Canal 6","19:22  Praça Rebouças / Canal 7 / Pça.Coração de Maria (Posto BR)","19:26  Pça. Coração de Maria / Av. dos Bancários","19:30  Av. Bartolomeu de Gusmão / FATEC / Praias / Gonzaga"]},{"numero":"15","nome":"Linha 15","ida":["05:25   Ferry Boat","05:32   Dino Bueno – Praça Rebouças","05:34   Pedro Lessa – Canal 6 – 5 – 4","05:35   Praça Palmares – Canal 3","05:40   Afonso Pena - Francisco Glicério até Canal 1","05:45   Canal 1 - Santa Casa – Praça dos Andradas","05:55   Posto Marilu","06:45   Metrô Conceição","07:10   Av. dos Bandeirantes – Berrine – Shopping Morumbi","07:15   Amaro Guerra - Alexandre Dumas – Luiz Seraphico Jr","07:25   Centro Africano - Av. João Dias – Cenesp (Supermercado EXTRA )","07:40   Ponte Transamérica – Nações Unidas - SP Market - Avon","07:55   Av. Interlagos (SANTANDER) - Nossa Senhora do Sabará – EMAE"],"volta":["17:05   Pte do socorro / Nações Unidas  s","17:15   Bento Branco de Andrade Filho","17:20   Av. João  Dias / CENESP P","17:22  Pte Transamérica / Cond. Panamérica / Santander","17:27   Nações Unidas / Ponto Carrefour r","17:32   Nações Unidas / Ponte do Morumbi","17:35   Dr Roberto Marinho / Chucri Zaidann","17:40   Av. Vicente Rao","17:50   Av. Cupece   e","18:10   Imigrantes (Altura da Kentinha) 19:05   Anchieta / Casqueiro","19:10   Posto Marilú","19:11   Martins Fontes / Cemitério do Saboó / Pça dos Andradas","19:15   Santa Casa / Canal 1","19:25   Av. Fco. Glicério / Afonso Pena até Canal 4","19:35   Pça Palmares","19:40   Av. Pedro Lessa até Canal 66","19:50   Av. Dino Bueno / Praça Rebouças / Av. dos Bancários","20:05   Ferry Boat  t"]},{"numero":"16","nome":"Linha 16","ida":["05:30   São Vicente / Sup. Carrefour","05:33   Av. da Praia / Divisa","05:35   Av. da Praia / Canal 1 / Canal 2","05:40   Av. da Praia / Canal 3 / Canal 4 / C.P.E (Quiosques)","05:45   Av. da Praia / Canal 6 / Epitácio Pessoa esq. Rua Trabulsi","05:50   Av. dos Bancários / Canal 7 / R. Fernando Costa – Ponta da Praia","05:55   Av. Pedro Lessa / Osvaldo Cochrane","06:00   Av. Afonso Pena / Pça Palmares – Canal 4","06:05   Av. Francisco Glicério / Canal 3 / Rua Azevedo Sodré","06:10   Rua Euclides da Cunha - Canal 1","06:15   Canal 1 / Carvalho de Mendonça","06:20   Canal 2 / Santa Casa","06:25   Túnel / Pça. dos Andradas / Marilu (pista do paredão)","06:30   Anchieta / 2ª Ponte do Casqueiro / Imigrantes","07:20   Metrô Imigrantes","08:15   Av. Estado - Metrô Barra Funda","08:45   Rua Vergueiro - Mêtro Sumaré"],"volta":["18:20   Metrô Imigrantes","19:20   Av. Martins Fontes / Marilú","19:25   Túnel / Santa Casa","19:30   Canal 2 / Rua Floriano Peixoto","19:35   Rua Floriano Peixoto / Galeão Carvalhal","19:40   Gov. Pedro de Toledo / Epitácio Pessoa - Canal 4","20:00   Eptácio Pessoa / Bancarios / Rei Alberto / Ferry Boat","20:05   Afonso Pena","20:15   Francisco Glicério 4","20:30   SV / Carrefour"]},{"numero":"17","nome":"Linha 17","ida":["06:15   Av. Rei Alberto - Ferry Boat","06:15   Av. Rei Alberto - Av. Gal San Martin (Canal 7)","06:16   Av. dos Bancários - Pça Coração de Maria (Padaria Luar de Prata)","06:17   Av. Dr. Epitácio Pessoa - Pizzaria Cristal","06:18   Av. Cel Joaquim Montenegro (canal 6)","06:20   Av. Cel Joaquim Montenegro (canal 6) - Av. Dr. Pedro Lessa","06:22   Av. Pedro Lessa - Av. Almirante Cochrane (Canal 5)","06:24   Av. Pedro Lessa - Av. Benjamim Constant","06:27   Av. Pedro Lessa - Av. Siqueira Campos (Canal 4)","06:28   Praça Palmares","06:29   Av. Afonso Pena - Av. Conselheiro Nébias","06:30   Francisco Glicério - Av. Washington Luís (Canal 3)","06:33   Francisco Glicério - Av. Dona Ana Costa/Extra","06:38   Francisco Glicério - Av. Sen. Pinheiro Machado (Canal 1)","06:39   Av. Sen. Pinheiro Machado (Canal 1) - R. Carvalho de Mendonça","06:42   Av. Dr. Cláudio Luís da Costa - Santa Casa","06:43   Av. Dr. Waldemar Leão - Av. Rangel Pestana","06:44   Pça dos Andradas - Rodoviária","06:48   Av. Martins Fontes - Pista Central","06:54   Via Anchieta - Passarela Casqueiro","07:50   Metrô Conceição","08:05   Metrô Imigrantes"],"volta":["18:00   Metrô Imigrantes","18:10   Rodovia dos Imigrantes","18:55   Via Anchieta - Bairro Jd. Casqueiro","19:05   Av. Martins Fontes","19:10   Pça dos Andradas – Rodoviária","19:15   Santa Casa","19:18   Av. Sen. Pinheiro Machado","19:25   Av. Francisco Glicério","19:25   Av. Afonso Pena / Senador Dantas","19:30   Av. Senador Dantas - até Pedro Lessa","19:35   Av. Pedro Lessa (Canal 5)","19:45   Av. Pedro Lessa - Av. Cel. Joaquim Montenegro (Canal 6)","19:48   Av. Cel. Joaquim Montenego (Canal 6) - Av. Dr. Epitácio Pessoa","19:55   Av. Epitácio Pessoa - Bancários até Ferry Boat","20:00   Ferry Boat - Volta pela praia até a divisa"]},{"numero":"18","nome":"Linha 18","ida":["06:00  Praia c/ Av. Ana Costa (sentido Praia)","06:01  Praia c/ Cons. Nébias","06:02  Praia c/ Oswaldo Cochrane","06:03   Praia c/ Alexandre Martins","06:05  Aquário - Carlos Campos até Rei Alberto","06:06   Rei Alberto até Fernando Costa","06:07  Praça Rebouças","06:10  Pedro Lessa até Canal 4 (Siqueira Campos)","06:20   Canal 4 até Bento de Abreu / Azevedo Sodré","06:25   Azevedo Sodré até Canal 3","06:25   Canal 3 até Alexandre Herculano","06:28   Francisco Glicério - Canal 3 - Av. Ana Costa - Canal 1","06:30   Senador Pinheiro (Canal 1)","06:32  Dr. Cláudio Luís da Costa - Santa Casa","06:33  Dr. Waldemar Leão – Túnel","06:35  Praça dos Andradas","06:46   Martins Fontes – Saboó","06:47   Ver. Alfredo das Neves - Posto Marilú","06:50   Anchieta – Casqueiro","07:35   Metrô Conceição","07:45   Metrô Imigantes"],"volta":["18:40   M. Conceição","19:40   Posto Marilú","19:42   Saboó","19:44   Rodoviária","19:45   Dr.Waldemar Leão – Túnel","19:48   Santa Casa","19:50   Canal 1","19:55   Av. Francisco Glicério  c/ Ana Costa","20:00   Alexandre Herculano – Washington Luis (Canal 3)","20:02   Washington Luis – Gov. Pedro de Toledo","20:05   Av. Epitácio Pessoa – Cons. Nébias","20:07   Av. Epitácio Pessoa– Siqueira Campos","20:10   Siqueira Campos (Canal 4)","20:15   Pedro Lessa – (Canal 5)","20:20   Pça. Rebouças – (Canal 7)","20:25   Gov. Fernando Costa – Rei Alberto","20:30   Ponta da Praia"]},{"numero":"19","nome":"Linha 19","ida":["05:05   Floriano Peixoto – Pça. da Independência","05:10   Galeão Carvalhal – Pedro de Toledo - Epitácio Pessoa","05:13   Av. dos Bancários – Rei Alberto","05:20   Ferry Boat","05:26   Av. da Praia – Canal 7 - 6 – 5 – 4","05:33   Av. da Praia - Canal 3 – 2","05:35   Canal 1 – Divisa – Itararé","05:40   Av. Presidente Wilson","05:45   Av. Antonio Emmerich","05:50   Cap. Luiz Hourneaux","05:57   Imigrantes – Cidade Náutica","06:50   Metrô Conceição","07:15   Av. dos Bandeirantes – Berrine – Shopping Morumbi","07:20   Amaro Guerra - Alexandre Dumas – Luiz Seraphico Jr","07:30   Centro Africano - Av. João Dias – Cenesp (Supermercado EXTRA )","07:45   Ponte Transamérica – Nações Unidas - SP Market - Avon","08:00   Av. Interlagos (SANTANDER) - Nossa Senhora do Sabará – EMAE"],"volta":["17:00   Av. Nossa Sra. do Sabará (EMAE) – Av. Interlagos (Santander)","17:05   Avon – SP Market – Nações Unidas","17:10   Ponte do Socorro – Ponte Transamérica","17:20   Bento Branco de Andrade Filho / Av. João Dias","17:25   Cenesp (Extra) / Cond. Panamérica – Santander","17:30   Nações Unidas – Estação Granja Julieta","17:35   Nações Unidas - Ponte do Morumbi","17:40   Engº Luiz Carlos Berrini","17:50   Av. Bandeirantes","18:10   Metrô Conceição","19:10   Imigrantes – Cidade Náutica - Cap. Luiz Hourneaux","19:20   Antonio Emmerich","19:25   Av. Pres. Wilson","19:30   Divisa Itararé – Canal 1","19:35   Canal 2 –3","19:45   Canal 4 – 5 – 6 - 7","20:00   Ferry Boat"]},{"numero":"21","nome":"Linha 21","ida":["05:25   Ferry Boat - Av. Rei Alberto I até Canal 6 - Canal 6 até Av. da Praiaa","05:27   Av. da Praia com Canal 6 - Canal 5 - Canal 4","05:32   Av. da Praia com Canal 3 - Canal 2","05:36   Av. da Praia com Canal 1","05:42   Praia do Itararé - Av. Pres. Wilson","05:45   Rua XV de Novembro - Cap. Mor Aguiar - Frei Gaspar","05:55   Cidade Náutica (Posto Imigrantes) )","06:45   Metrô Conceição","07:00   Metrô Imigrantess"],"volta":["15:00   Metrô Imigrantes s","16:10   Av. Martins Fontes - Posto Marilú","16:20   Túnel - Santa Casa - Canal 1 1","16:25   Av. Francisco Glicério","16:35   Av. Afonso Pena - Av. Pedro Lessa - Av. Epitácio Pessoaa","16:45   Ferry Boat","16:55   Av. da Praia até Pres. Wilson - Antonio Emmerick k"]},{"numero":"22","nome":"Linha 22","ida":["05:40  Ferry Boat","05:43  Av. da Praia com Canal 6 - 5- 4","05:48  Av. da Praia com Canal 3 – 2","05:50  Av. da Praia com Canal 1","05:52  Praia do Itararé - Av. Pres. Wilson","06:10  Av. Antonio Emmerick (Barateiro)","06:15  Cidade Náutica (Posto Imigrantes)","07:20  Metrô Conceição","07:35  Metrô Imigrantes"],"volta":["18:30  Metrô Conceição","19:45  Cidade Náutica (Posto Imigrantes) até Barateiro","20:00  Av. Antonio Emmerick até Av. Pres. Wilson","20:15  Av. Pres. Wilson até Praia do Itararé","20:25  Praia (Canais 1 - 2 - 3 - 4 - 5 - 6 - 7 )","20:40  Ferry Boat"]},{"numero":"23","nome":"Linha 23","ida":["05:50  Ferry Boat Av. Rei Alberto I até Canal 6 - Canal 6 até Av. da Praia","05:55  Av. da Praia Canal 6 - 5 -4","06:00  Av. da Praia Canal 3 - 2","06:05  Av. da Praia Canal 1","06:10  Praia do Itararé - Av. Pres. Wilson","06:15  Av. Pres. Wilson - Antonio Emmerick","06:30  Antonio Emmerick - N.S. de Fátima - Posto Marilú","07:15  Metrô Imigrantes"],"volta":["17:50 Metrô Imigrantes","19:05 Posto Marilú","19:15 Av. N. S. De Fátima - Av. Antonio Emmerick","19:20 Av. Antonio Emmerick até Av. Pres. Wilson","19:25 Av. Pres. Wilson até Praia do Itararé","19:30 Praia - Canal 1"]},{"numero":"24","nome":"Linha 24","ida":["06:35   Ferry Boat - Av. da Praia até Canal 4","06:45   Canal 4 até Rua Dr. Bento de Abreu - Azevedo Sodré","06:50   Rua Euclides da Cunha até Canal 1 - Canal 1 até Av. da Praia - Praia do Itararé","06:55   Av. Presidente Wilson","07:05   Av. Antonio Emmerick (Barateiro)","07:15   Cidade Náutica (Posto Imigrantes)","08:10   Metrô Conceição","08:20   Metrô Imigrantes"],"volta":["17:50   Metrô Conceição","18:50   Cidade Náutica","18:55   Linha Amarela","19:00   Av. Antonio Emmerick até Av. Pres. Wilson","19:10   Av. Pres. Wilson até Praia do Itararé","19:20   Praia – Canal 1"]},{"numero":"26","nome":"Linha 26","ida":["05:10   Rua Padre Anchieta - Av. Pres. Wilson - Posto Shell","05:25   Av. da Praia até Divisa","05:27   Av. Ana Costa - Galeão Carvalhal - Pedro de Toledo","05:35   Av. Epitácio Pessoa até canal 6 - Bancários","05:40   Rei Alberto - Fernando Costa - Praça Rebouças - Pedro Lessa até Canal 6","05:55   Av. Afonso Pena - Canal 6 - 5 - 4 - Av. Conselheiro Nébias","06:00   Av. Francisco Glicério - Canal 1","06:10   Canal 1 - Santa Casa - Praça dos Andradas","06:15   Posto Marilú","07:00   Metrô Imigrantes","07:20   Ricardo Jafet  –  Av. Tereza Cristina –  Av. Estado","07:40   Av. Cruzeiro do Sul – Av.Zaki Narchi07:45   Ericsson – Terminal Rodoviário Tiête"],"volta":["18:40   Metrô Imigrantes","19:40   Posto Marilú - Saboó","19:45   Túnel - Santa Casa - Canal 1","20:10   Av. Francisco Glicério - Av. Pedro Lessa até Canal 6","20:25   Canal 6 - Av. da Praia até Canal 1","20:40   Divisa - Av. Pres. Wilson"]},{"numero":"27","nome":"Linha 27","ida":["06:08  Av. Epitácio Pessoa - Oswaldo Cochrane","06:15  Av. Epitácio Pessoa até Canal 6 - Dino Bueno","06:18  Praça Rebouças - Av. Aristóteles Menezes","06:25  Av. Pedro Lessa até Canal 4","06:28  Rua Goiás - Av. Ana Costa","06:30  Av. Francisco Glicério","06:35  Canal 1","06:42  Canal 1 - Santa Casa - Praça dos Andradas","06:45  Posto Marilú","07:40  Metrô Conceição","07:55  Metrô Imigrantes  s","08:10  Av. do Estado - CTO Itaú","08:15  Barão Jaguara - Metrô Brás   s"],"volta":["18:20  Metrô Brás -","18:25  CTO Itaú","18:35  Av. Pres. Wilson","19:00  Bolsão Imigrantes","20:00  Posto Marilú - Saboó","20:10  Túnel - Santa Casa - Canal 1","20:15  Av. Francisco Glicério - Alexandre Herculano - Afonso Pena  a","20:25  Av. Pedro Lessa até Canal 6","20:30  Praça Rebouças - Dino Bueno – Bancários s","20:35  Av. da Praia até Canal 4"]},{"numero":"28","nome":"Linha 28","ida":["05:40   Ferry Boat\u001f","05:45   Praia até Canal 6","06:00   Praia até Canal 1","06:05   Canal 2 - 1 - Divisa - Itararé - Pres. Wilson","06:20   Antonio Emmerich - Barateiro - Cidade Náutica","07:10   Metrô Conceição","07:50   Av. dos Bandeirantes - Berrini - Shopping Morumbi\u001f","07:55   Amaro Guerra - Alexandre Dumas - Carrefour","08:10   Av. João Dias – Cenesp","08:20   Ponte Transamérica - Satander","08:10   Av. João Dias – Cenesp","08:20   Ponte Transamérica - Santander"],"volta":["17:55   Av. João Dias","18:00   CENESP (Extra)","18:05   Ponte Transamérica - Santander - Av. Nações Únidas","18:10   Marginal Pinheiros - Carrefour","18:15   Ponte do Morumbi\u001f","18:18   Berrini","18:30   Bandeirantes","18:55   Metrô Conceição","20:00   Cidade Náutica - Barateiro - Antonio Emmerich","20:10   Av. Pres. Wilson - Itararé - Divisa","20:25   Canal 1 - 2 - 3- 4 - 5 - 6 – 7","20:30   Ferry Boat"]},{"numero":"29","nome":"Linha 29","ida":["05:15  Canal 3 c/ Pedro de Toledo","05:23  Av. Epitácio Pessoa / Canal 7 /Ferry Boat","05:30  Av. Pedro Lessa / Canal 4","05:35  Goiás / R. Pedro Américo até Canal 2","05:38  Canal 2 /Joaquim Távora / Canal 1 até a Praia","05:45  Av. da Praia / Av. Pres. Wilson /SV","05:55  Av. Antonio Emmerich / Av. Penedo / Av. Augusto Severo / Náutica","06:10  Rod. dos Imigrantes","06:55  Metrô Conceição","07:15  Bandeirantes (Bolsão)","07:25  Hebraica","07:28  Pinheiros","07:45  Av. Jaguaré até Hipermercado Extra","07:50  Av. Drº Candido Mota Filho / Pça. Conde Luiz Eduardo Matarazzo","07:55  Av. Martin Luther King / Rua Bezerra de Menezes (Bradesco)","08:00  Av. Yara (Fundação Bradesco)","08:05  Av. Dep. Emilio Carlos","08:10  Av. Bussocaba até Rodoviária de Osasco"],"volta":["16:30   Rod. Osasco / Av. Bussocaba / Av. Martin Luther King","17:03   Av. Bezerra de Menezes (Bradesco) / Av. Yara / Fundação Bradesco","17:08   Terminal Vila Yara / Rua Leão Machado (Shop. Continental)","17:10   Pça. Willian Kall/ Av. A. de Souza Noshese / R. Andréia Bolgi / Rua São Fidélis","17:15   Av. Alexandre Mackenzie (Bunge) até Marginal Pinheiros","18:10   Cid. Jardim","18:15   Hebraíca","18:25   Pinheiros","19:15   Metrô Conceição","20:30   São Vicente / Av. Augusto Severo / Av. Antonio Emmerich","20:50   Av. Pres. Wilson até a Praia do Itararé","21:00   Divisa Santos - São Vicente","21:15   Canal 1 até Francisco Glicério","21:20   Av. Francisco Glicério / Av. Afonso Pena / Senador Dantas","21:25   Av. Pedro Lessa / Praça Rebouças","21:35   Ferry Boat"]},{"numero":"31","nome":"Linha 31","ida":["06:00   Jd. Pernambuco II","06:05   Jd. Acapulco","06:15   Enseada","06:20   Av. D. Pedro I","06:23   Av. Mal Deodoro da Fonseca - Rua Mario Ribeiro","06:30   Av. Puglisi","06:35   Rodoviária","06:40   Rodovia Piaçaguera","07:45   Metrô Conceição","08:00  Metrô Imigrantes"],"volta":["18:50   Metrô Conceição","19:45   Rodovia Piaçaguera","19:50   Rodoviária","19:55   Av. Puglisi","20:00   Av. Mal. Deodoro da Fonseca","20:05   Av. D. Pedro I","20:10   Enseada","20:15   Jd. Acapulco - Jd.Pernambuco II"]},{"numero":"32","nome":"Linha 32","ida":["05:40   Ferry Boat","05:42   Av. Adhemar de Barros até Posto da Ultragaz","05:45   Av. dos Caiçara - Praça Walter Belian","05:50   Av. G. Rondon","05:53   Av. Mal Deodoro da Fonseca - Av. Leomil","05:55   Av. Puglisi - Rodoviária - Av. Santos Dumont","06:10   Praça 14 Bis - Av. Pres. Vargas","06:15   Trevo - Vicente de Carvalho","07:15   Metrô Conceição","07:30   Metrô Imigrantes"],"volta":["17:55   Metrô Conceição","18:55   VICENTE DE CARVALHO - Av. Pres. Vargas - Praça 14 Bis","19:10   Av. Santos Dumont – Rodoviária","19:15   Av. Puglisi - Leomil - Mal. Deodoro da Fonseca - Av. dos Caiçaras","19:25   Av. Manoel Albino - Av. Adhemar de Barros"]},{"numero":"33","nome":"Linha 33","ida":["05:00  Estrada de Pernambuco - KM 7 -Jd. Pernambuco II - Jd. Acapulco","05:05  Praia da Enseada - Unaerp","05:15  Av. D. Pedro I - Mario Ribeiro - Leomil - Gal. Rondon","05:30  Praça Walter Belian - Av. Caiçara - Manoel Albino","05:35  Av. Adhemar de Barros","05:40  Rodoviária","05:45  Av. Santos Dumont","05:50  Praça 14 Bis - Av. Pres. Vargas","05:55  Teatro (Vicente de Carvalho)","06:55  Metrô Conceição","07:20  Av. dos Bandeirantes - Berrini - Shopping Morumbi","07:50  Cenesp"],"volta":["17:05  Cenesp - Ponte João Dias - José Guerra","17:10  Alexandre Dumas - Marg. Pinheiros - Berrini","17:30  Bandeirantes","19:10  Trevo (Vicente de Carvalho)","19:15  Av. Pres. Vargas - Praça 14 Bis","19:25  Av. Santos Dumont – Rodoviária","19:30  Av. Adhemar de Barros - Caiçaras","19:40  Praça Walter Belian - Gal. Rondon – Leomil","19:50  Puglisi - Mal. Deodoro da Fonseca - D. Pedro I","20:15  Unaerp - Estrada do Pernambuco KM7"]},{"numero":"34","nome":"Linha 34","ida":["05:10   Morrinhos – CDHU","05:20   Praia da Enseada - Unaerp","05:25   Av. D. Pedro I","05:30   Hospital Santo Amaro - Av. Montenegro","05:35   Rodoviária","05:40   Av. Santos Dumont","05:45   Praça 14 Bis - Av. Pres. Vargas","05:50   Trevo (Vicente de Carvalho)","07:00   Metrô Conceição","07:20   Bandeirantes","07:50   Marg. Pinheiros - Pedroso de Moraes - Praça do Correio"],"volta":["17:15   Bolsão Hebraica  a","17:45   M. Pinheiros","18:00   Bandeirantes","18:10   M. Conceição","19:15   Trevo (Vicente de Carvalho)","19:20   Av. Pres. Vargas - Praça 14 Bis","19:30   Av. Santos Dumont – Rodoviária","19:40   Puglisi -Av. Montenegro - Hospital Santo Amaro","19:50   Av. D. Pedro I","20:00   Unaerp - Enseada","20:10   Morrinhos – CDHU"]},{"numero":"35","nome":"Linha 35","ida":["05:10  Morrinhos","05:20  Praia da Enseada - UNAERP","05:30  Av. D. Pedro I - Mario Ribeiro - Leomil - Gal. Rondon","05:35  Praça Walter Belian - Av. Caiçara","05:40  Av. Helena Maria até Av. Adhemar de Barros","05:40  Rodoviária","05:50  Praça 14 Bis - Av. Pres. Vargas","05:55  Av. Pres. Vargas c/ Oswaldo Cruz","06:00  Teatro (Vicente de Carvalho)","07:00  Metrô Conceição","07:05  Pedro Bueno – Tamoios – Congonhas","07:35  Bandeirantes - Berrine"],"volta":["17:55  Aeroporto – Pedro Buenoo","18:30  Metrô Conceição","19:30  Trevo (Vicente de Carvalho) )","19:40  Av. Pres. Vargas - Praça 14 Bis","19:50  Av. Santos Dumont – Rodoviária a","20:00  Av. Adhemar de Barros – Caiçaras – Ferry Boat","20:10  Praça Walter Belian - Gal. Rondon – Leomil l","20:15  Puglisi - Mal. Deodoro da Fonseca - D. Pedro I","20:30  UNAERP  P"]},{"numero":"41","nome":"Linha 41","ida":["06:25  Metrô Conceição","06:30  Metrô Jabaquara","07:30 Av. Martins Fontes (Posto Marilú)","07:35  Rodoviária (Praça dos Andradas)","07:38  Rua Amador Bueno","07:40  Rua Brás Cubas","07:43  Joaquim Távora","07:48  Av. Ana Costa (até Praça da Independência)"],"volta":["17:35  Av. Ana Costa (Banco do Brasil)","17:45  Rua Lucas Fortunato","17:50  Brás Cubas","18:00  João Pessoa (Marisa)","18:02  Praça dos Andradas","18:11  Av. Martin Fontes (Marilú)","18:55  Metrô Jabaquara","19:05  Metrô Conceição"]},{"numero":"42","nome":"Linha 42","ida":[],"volta":["20:00   Metrô Conceição","21:00   Av. Martins Fontes (Posto Marilú)","21:15   Túnel – Santa Casa – Canal 1","21:20   Av. Francisco Glicério / Afonso Pena","21:25   Senador Dantas","21:30   Pedro Lessa até Ferry Boat","21:35   Av. da Praia até São Vicente (Av. Pres. Wilson / Av. Antonio Emmerick))"]}]}